downloader/__init__.py
fileDownloader/__init__.py
fileDownloader/fd_s3.py
fileDownloader/fileDownloader.py
fileDownloader.py-0.4.1.dist-info/METADATA
fileDownloader.py-0.4.1.dist-info/RECORD
fileDownloader.py-0.4.1.dist-info/WHEEL
fileDownloader.py-0.4.1.dist-info/top_level.txt
