Metadata-Version: 2.1
Name: fileDownloader.py
Version: 0.4.1
Summary: Downloads files via HTTP or FTP
Home-page: http://bantonj.wordpress.com/software/open-source/
Author: Joshua Banton
Author-email: bantonj@gmail.com
License: MIT
Download-URL: http://code.google.com/p/filedownload/downloads/list
Keywords: download
Platform: UNKNOWN
Classifier: Programming Language :: Python
Classifier: Topic :: Software Development :: Libraries :: Python Modules
